{
  "name": "Knowledge Stone",
  "type": "consumable",
  "_id": "nL9IALzm9BNi5oSt",
  "img": "icons/commodities/treasure/token-engraved-blue-glowing.webp",
  "system": {
    "description": "<p>If you die while holding this stone, an ally can take a card from your loadout to place in their loadout or vault. After they take this knowledge, the stone crumbles.</p>",
    "quantity": 1,
    "actions": {
      "We38aIuxBrv8zhfr": {
        "type": "effect",
        "_id": "We38aIuxBrv8zhfr",
        "systemPath": "actions",
        "description": "",
        "chatDisplay": true,
        "actionType": "action",
        "cost": [],
        "uses": {
          "value": null,
          "max": null,
          "recovery": null
        },
        "effects": [],
        "target": {
          "type": null,
          "amount": null
        },
        "name": "Use",
        "img": "icons/commodities/treasure/token-engraved-blue-glowing.webp",
        "range": ""
      }
    },
    "consumeOnUse": true
  },
  "effects": [],
  "folder": null,
  "sort": 0,
  "ownership": {
    "default": 0,
    "OFxauskoxcvVTVNA": 3
  },
  "flags": {},
  "_stats": {
    "compendiumSource": null,
    "duplicateSource": null,
    "exportSource": null,
    "coreVersion": "13.344",
    "systemId": "daggerheart",
    "systemVersion": "0.0.1",
    "createdTime": 1753592240392,
    "modifiedTime": 1753592383492,
    "lastModifiedBy": "OFxauskoxcvVTVNA"
  },
  "_key": "!items!nL9IALzm9BNi5oSt"
}
