{
  "name": "Hold the Line",
  "img": "icons/svg/item-bag.svg",
  "type": "domainCard",
  "folder": "8DOVMjTtZFKtwX4p",
  "system": {
    "description": "<p><p class=\"Body-Foundation\">Describe the defensive stance you take and <strong>spend a </strong><tooltip category=\"rule\" class=\"tooltip-convert\" element=\"hope\" nexus=\"daggerheart\"><strong>Hope</strong></tooltip>. If an adversary moves within <tooltip category=\"rule\" class=\"tooltip-convert\" element=\"very-close\" nexus=\"daggerheart\">Very Close</tooltip> range, they’re pulled into <tooltip category=\"rule\" class=\"tooltip-convert\" element=\"melee\" nexus=\"daggerheart\">Melee</tooltip> range and <tooltip category=\"rule\" class=\"tooltip-convert\" element=\"restrained\" nexus=\"daggerheart\"><em>Restrained</em></tooltip><em>.</em></p><p class=\"Body-Foundation\">This <tooltip category=\"rule\" class=\"tooltip-convert\" element=\"condition\" nexus=\"daggerheart\">condition</tooltip> lasts until you move or fail a roll with <tooltip category=\"rule\" class=\"tooltip-convert\" element=\"fear\" nexus=\"daggerheart\">Fear</tooltip>, or the GM spends 2 Fear on their turn to clear it.</p></p>",
    "domain": "valor",
    "recallCost": 1,
    "level": 9,
    "type": "ability",
    "actions": {
      "hxupFx3czFHz3xfG": {
        "type": "effect",
        "_id": "hxupFx3czFHz3xfG",
        "systemPath": "actions",
        "description": "",
        "chatDisplay": true,
        "actionType": "action",
        "cost": [
          {
            "keyIsID": false,
            "key": "hope",
            "value": 1,
            "scalable": false,
            "step": null
          }
        ],
        "uses": {
          "value": null,
          "max": "",
          "recovery": null
        },
        "effects": [],
        "target": {
          "type": "self",
          "amount": null
        },
        "name": "Spend Hope",
        "img": "icons/magic/holy/barrier-shield-winged-blue.webp",
        "range": ""
      }
    }
  },
  "flags": {},
  "_stats": {
    "compendiumSource": null,
    "duplicateSource": null,
    "exportSource": null,
    "coreVersion": "13.346",
    "systemId": "daggerheart",
    "systemVersion": "0.0.1",
    "createdTime": 1753922784468,
    "modifiedTime": 1754069423419,
    "lastModifiedBy": "MQSznptE5yLT7kj8"
  },
  "_id": "kdFoLo3KXwn4LqTG",
  "sort": 3400000,
  "effects": [
    {
      "name": "Hold The Line",
      "type": "base",
      "system": {
        "rangeDependence": {
          "enabled": false,
          "type": "withinRange",
          "target": "hostile",
          "range": "melee"
        }
      },
      "_id": "zQAyz8X0IdCNoEj1",
      "img": "icons/magic/defensive/shield-barrier-glowing-blue.webp",
      "changes": [],
      "disabled": true,
      "duration": {
        "startTime": null,
        "combat": null,
        "seconds": null,
        "rounds": null,
        "turns": null,
        "startRound": null,
        "startTurn": null
      },
      "description": "<p><span class=\"Body-Foundation\" style=\"box-sizing:border-box;margin:0px;scrollbar-width:thin;scrollbar-color:rgb(93, 20, 43) rgba(0, 0, 0, 0);font-family:Montserrat, sans-serif;color:rgb(239, 230, 216);font-size:14px;font-style:normal;font-variant-ligatures:normal;font-variant-caps:normal;font-weight:400;letter-spacing:normal;orphans:2;text-align:start;text-indent:0px;text-transform:none;widows:2;word-spacing:0px;-webkit-text-stroke-width:0px;white-space:normal;background-color:rgba(24, 22, 46, 0.376);text-decoration-thickness:initial;text-decoration-style:initial;text-decoration-color:initial\">If an adversary moves within Very Close range, they’re pulled into Melee range and <em style=\"box-sizing:border-box;scrollbar-width:thin;scrollbar-color:rgb(93, 20, 43) rgba(0, 0, 0, 0)\">Restrained.</em>This condition lasts until you move or fail a roll with Fear, or the GM spends 2 Fear on their turn to clear it.</span></p>",
      "origin": null,
      "tint": "#ffffff",
      "transfer": true,
      "statuses": [],
      "sort": 0,
      "flags": {},
      "_stats": {
        "compendiumSource": null,
        "duplicateSource": null,
        "exportSource": null,
        "coreVersion": "13.346",
        "systemId": "daggerheart",
        "systemVersion": "0.0.1",
        "createdTime": 1754069430126,
        "modifiedTime": 1754069487014,
        "lastModifiedBy": "MQSznptE5yLT7kj8"
      },
      "_key": "!items.effects!kdFoLo3KXwn4LqTG.zQAyz8X0IdCNoEj1"
    }
  ],
  "ownership": {
    "default": 0
  },
  "_key": "!items!kdFoLo3KXwn4LqTG"
}
