{
  "type": "Item",
  "folder": "yPVeShe47ETIqs9q",
  "name": "Level 6",
  "color": null,
  "sorting": "a",
  "_id": "nKCmeAn7ESsb4byE",
  "description": "",
  "sort": 600000,
  "flags": {},
  "_stats": {
    "compendiumSource": null,
    "duplicateSource": null,
    "exportSource": null,
    "coreVersion": "13.346",
    "systemId": "daggerheart",
    "systemVersion": "0.0.1",
    "lastModifiedBy": "YNJ4HgHtFrTI89mx",
    "modifiedTime": 1752681584076
  },
  "_key": "!folders!nKCmeAn7ESsb4byE"
}
